[{"\u015eanl\u0131urfa": 46.78, "Ayd\u0131n": 29.72, "Zonguldak": 38.26, "Rize": 66.38, "Bart\u0131n": 42.62, "K\u0131r\u0131kkale": 50.6, "Antalya": 35.28, "Yozgat": 58.12, "Ad\u0131yaman": 58.0, "Amasya": 45.87, "Kayseri": 53.59, "K\u0131rklareli": 23.7, "Yalova": 39.73, "Afyonkarahisar": 52.3, "Kastamonu": 48.72, "Ardahan": 26.76, "Samsun": 52.88, "Erzincan": 49.22, "Hatay": 38.06, "Aksaray": 58.31, "G\u00fcm\u00fc\u015fhane": 58.06, "K\u0131r\u015fehir": 39.84, "Mersin": 26.42, "Mu\u011fla": 26.93, "Eski\u015fehir": 36.24, "Bursa": 43.99, "Nev\u015fehir": 52.4, "Denizli": 39.78, "Gaziantep": 47.03, "Karab\u00fck": 47.95, "Sivas": 57.51, "Siirt": 28.71, "U\u015fak": 38.29, "\u0130stanbul": 41.11, "Ankara": 41.4, "Artvin": 39.97, "Kocaeli": 46.41, "A\u011fr\u0131": 16.63, "Kilis": 49.2, "Hakkari": 9.7, "Sinop": 47.54, "Karaman": 55.4, "Adana": 30.38, "Bolu": 51.95, "Erzurum": 51.97, "Edirne": 24.77, "\u00c7anakkale": 34.56, "Bilecik": 38.44, "Kars": 27.17, "Van": 20.07, "Manisa": 37.13, "I\u011fd\u0131r": 12.01, "Trabzon": 55.29, "Ni\u011fde": 47.9, "Kahramanmara\u015f": 60.79, "Tunceli": 11.52, "Malatya": 58.42, "\u0130zmir": 26.76, "Diyarbak\u0131r": 14.81, "Konya": 65.09, "Ordu": 52.93, "Burdur": 44.13, "Sakarya": 56.5, "Elaz\u0131\u011f": 52.85, "Bitlis": 32.08, "Batman": 18.89, "D\u00fczce": 59.17, "\u00c7ank\u0131r\u0131": 59.2, "Giresun": 53.52, "Tokat": 51.58, "Bayburt": 60.02, "Osmaniye": 39.1, "\u015e\u0131rnak": 9.71, "Bing\u00f6l": 48.1, "K\u00fctahya": 54.49, "Mardin": 19.91, "\u00c7orum": 59.13, "Tekirda\u011f": 31.59, "Bal\u0131kesir": 40.06, "Isparta": 45.31, "Mu\u015f": 24.86}]